README.md
setup.cfg
setup.py
dict_config_parser/__init__.py
dict_config_parser.egg-info/PKG-INFO
dict_config_parser.egg-info/SOURCES.txt
dict_config_parser.egg-info/dependency_links.txt
dict_config_parser.egg-info/top_level.txt