Metadata-Version: 2.1
Name: dict-config-parser
Version: 1.0
Summary: A custom wrapper, written in python, for reading and writing ini files, using simple dictionaries.
Home-page: https://github.com/thefakhir/dict_config_parser.git
Author: M Fakhir Khan
Author-email: thefakhir@gmail.com
License: UNKNOWN
Keywords: config parser configparser
Platform: UNKNOWN
Requires-Python: >=3.5, <3.8
